README.md
setup.cfg
setup.py
videocr/__init__.py
videocr/api.py
videocr/constants.py
videocr/models.py
videocr/opencv_adapter.py
videocr/utils.py
videocr/video.py
videocr.egg-info/PKG-INFO
videocr.egg-info/SOURCES.txt
videocr.egg-info/dependency_links.txt
videocr.egg-info/requires.txt
videocr.egg-info/top_level.txt