Metadata-Version: 2.1
Name: videocr
Version: 0.1.6
Summary: Extract hardcoded subtitles from videos using machine learning
Home-page: https://github.com/apm1467/videocr
Author: Yi Ge
Author-email: me@yige.ch
License: MIT
Download-URL: https://github.com/apm1467/videocr/archive/v0.1.6.tar.gz
Platform: UNKNOWN
Classifier: Development Status :: 3 - Alpha
Classifier: Intended Audience :: Developers
Classifier: License :: OSI Approved :: MIT License
Classifier: Programming Language :: Python :: 3
Classifier: Programming Language :: Python :: 3.7
